etest/__init__.py
etest/ebuild.py
etest/information.py
etest/overlay.py
etest/tests.py
etest/docker/__init__.py
etest/docker/common.py
etest/docker/container.py
etest/docker/image.py
etest/lexers/__init__.py
etest/lexers/bash.py
etest/parsers/__init__.py
etest/parsers/bash.p
etest/parsers/bash.py
etest-1.0.0.data/data/share/doc/etest-1.0.0/README.rst
etest-1.0.0.dist-info/DESCRIPTION.rst
etest-1.0.0.dist-info/METADATA
etest-1.0.0.dist-info/RECORD
etest-1.0.0.dist-info/WHEEL
etest-1.0.0.dist-info/entry_points.txt
etest-1.0.0.dist-info/metadata.json
etest-1.0.0.dist-info/top_level.txt
test_etest/__init__.py
test_etest/test_common.py
test_etest/test_helpers.py
test_etest/test_fixtures/__init__.py
test_etest/test_fixtures/test_ebuilds/08a3cac2fae94e3d8f72ab3d49266b30.py
test_etest/test_fixtures/test_ebuilds/5efda208255149dcb4777b869d98482e.py
test_etest/test_fixtures/test_ebuilds/8b4f1dd596e641aa87aca835809043aa.py
test_etest/test_fixtures/test_ebuilds/__init__.py
test_etest/test_fixtures/test_ebuilds/eab5f11185a74264acb98eeb95b3238f.py
test_etest/test_fixtures/test_scripts/032bfd4400a74dee8d41ac515a56a44b.py
test_etest/test_fixtures/test_scripts/0431e3bee752482986467023e54b4673.py
test_etest/test_fixtures/test_scripts/04ec19a6834e4f4688a4e947a90826ce.py
test_etest/test_fixtures/test_scripts/0c486b86149342bdba2e9b32428d73d1.py
test_etest/test_fixtures/test_scripts/14c46139340a4ca9a266b37a80e74533.py
test_etest/test_fixtures/test_scripts/19310cb9eefb40e3a1a008ab8b9013c8.py
test_etest/test_fixtures/test_scripts/232f4c230eeb4549bd869d475cc97163.py
test_etest/test_fixtures/test_scripts/345a0acee57345389c8aa82171d3d954.py
test_etest/test_fixtures/test_scripts/3615a376b3fc45b7ab2a5b29ff4a30bc.py
test_etest/test_fixtures/test_scripts/3cbefae6b9e8430d869d836352347c0e.py
test_etest/test_fixtures/test_scripts/40e465907f16472db2828d3998a03ae0.py
test_etest/test_fixtures/test_scripts/41299eac663144e5aabcf25fa907aa19.py
test_etest/test_fixtures/test_scripts/419f4873d82340699c55000386901621.py
test_etest/test_fixtures/test_scripts/41a217e3097c487b8a0ecc1ffc7ffe40.py
test_etest/test_fixtures/test_scripts/47c908515a97487a8ce309eaa7ac3081.py
