Metadata-Version: 2.0
Name: etest
Version: 1.0.0
Summary: Ebuild Testing Framework
Home-page: https://github.com/alunduil/etest
Author: Alex Brandt
Author-email: alunduil@gentoo.org
License: MIT
Keywords: ebuild,test,gentoo,portage,emerge
Platform: UNKNOWN
Classifier: Development Status :: 3 - Alpha
Classifier: Environment :: Console
Classifier: Intended Audience :: Developers
Classifier: Intended Audience :: System Administrators
Classifier: License :: OSI Approved :: MIT License
Classifier: Natural Language :: English
Classifier: Operating System :: POSIX :: Linux
Classifier: Programming Language :: Python
Classifier: Programming Language :: Python :: 3
Classifier: Programming Language :: Python :: 3.3
Classifier: Programming Language :: Python :: 3.4
Classifier: Programming Language :: Python :: 3.5
Classifier: Programming Language :: Python :: Implementation :: CPython
Classifier: Topic :: Software Development :: Quality Assurance
Classifier: Topic :: Software Development :: Testing
Classifier: Topic :: Utilities
Requires-Dist: click
Requires-Dist: docker-py
Requires-Dist: ply
